flowmaestro/__init__.py
flowmaestro/client.py
flowmaestro/py.typed
flowmaestro/_http/__init__.py
flowmaestro/_http/async_client.py
flowmaestro/_http/sse_client.py
flowmaestro/_http/sync_client.py
flowmaestro/errors/__init__.py
flowmaestro/resources/__init__.py
flowmaestro/resources/agents.py
flowmaestro/resources/executions.py
flowmaestro/resources/knowledge_bases.py
flowmaestro/resources/threads.py
flowmaestro/resources/triggers.py
flowmaestro/resources/webhooks.py
flowmaestro/resources/workflows.py
flowmaestro/types/__init__.py
flowmaestro-0.1.0.dist-info/METADATA
flowmaestro-0.1.0.dist-info/WHEEL
flowmaestro-0.1.0.dist-info/RECORD
