Metadata-Version: 2.4
Name: flowmaestro
Version: 0.1.0
Summary: Official Python SDK for FlowMaestro
Project-URL: Homepage, https://flowmaestro.io
Project-URL: Documentation, https://flowmaestro.io/docs/sdk/python
Project-URL: Repository, https://github.com/flowmaestro/flowmaestro
Project-URL: Issues, https://github.com/flowmaestro/flowmaestro/issues
Author-email: FlowMaestro Team <support@flowmaestro.io>
License-Expression: MIT
Keywords: agents,ai,automation,flowmaestro,sdk,workflow
Classifier: Development Status :: 4 - Beta
Classifier: Intended Audience :: Developers
Classifier: License :: OSI Approved :: MIT License
Classifier: Operating System :: OS Independent
Classifier: Programming Language :: Python :: 3
Classifier: Programming Language :: Python :: 3.9
Classifier: Programming Language :: Python :: 3.10
Classifier: Programming Language :: Python :: 3.11
Classifier: Programming Language :: Python :: 3.12
Classifier: Programming Language :: Python :: 3.13
Classifier: Typing :: Typed
Requires-Python: >=3.9
Requires-Dist: httpx-sse>=0.4.0
Requires-Dist: httpx>=0.25.0
Provides-Extra: dev
Requires-Dist: mypy>=1.0.0; extra == 'dev'
Requires-Dist: pytest-asyncio>=0.21.0; extra == 'dev'
Requires-Dist: pytest-httpx>=0.30.0; extra == 'dev'
Requires-Dist: pytest>=7.0.0; extra == 'dev'
Requires-Dist: ruff>=0.1.0; extra == 'dev'
